citations_count/__init__.py
citations_count/config.py
citations_count/core.py
citations_count/logging_utils.py
citations_count/sources/__init__.py
citations_count/sources/crossref.py
citations_count/sources/googlescholar.py
citations_count/sources/opencitations.py
citations_count-1.0.0.dist-info/licenses/LICENSE
citations_count-1.0.0.dist-info/METADATA
citations_count-1.0.0.dist-info/WHEEL
citations_count-1.0.0.dist-info/top_level.txt
citations_count-1.0.0.dist-info/RECORD
