Metadata-Version: 2.4
Name: citations-count
Version: 1.0.0
Summary: Fetch citation counts from CrossRef, OpenCitations, and Google Scholar.
Author-email: Ezequiel Santos <ezequiel.ifsp@gmail.com>
License: MIT License
Project-URL: Homepage, https://github.com/ezefranca/citations_count_lib
Requires-Python: >=3.8
License-File: LICENSE
Requires-Dist: requests
Requires-Dist: beautifulsoup4
Requires-Dist: pandas
Dynamic: license-file
